spacex/api/common/status/status_pb2.py
spacex/api/common/status/status_pb2.pyi
spacex/api/common/status/status_pb2_grpc.py
spacex/api/common/status/__pycache__/status_pb2.cpython-313.pyc
spacex/api/device/command_pb2.py
spacex/api/device/command_pb2.pyi
spacex/api/device/command_pb2_grpc.py
spacex/api/device/common_pb2.py
spacex/api/device/common_pb2.pyi
spacex/api/device/common_pb2_grpc.py
spacex/api/device/device_pb2.py
spacex/api/device/device_pb2.pyi
spacex/api/device/device_pb2_grpc.py
spacex/api/device/dish_config_pb2.py
spacex/api/device/dish_config_pb2.pyi
spacex/api/device/dish_config_pb2_grpc.py
spacex/api/device/dish_pb2.py
spacex/api/device/dish_pb2.pyi
spacex/api/device/dish_pb2_grpc.py
spacex/api/device/rssi_scan_pb2.py
spacex/api/device/rssi_scan_pb2.pyi
spacex/api/device/rssi_scan_pb2_grpc.py
spacex/api/device/transceiver_pb2.py
spacex/api/device/transceiver_pb2.pyi
spacex/api/device/transceiver_pb2_grpc.py
spacex/api/device/wifi_config_pb2.py
spacex/api/device/wifi_config_pb2.pyi
spacex/api/device/wifi_config_pb2_grpc.py
spacex/api/device/wifi_pb2.py
spacex/api/device/wifi_pb2.pyi
spacex/api/device/wifi_pb2_grpc.py
spacex/api/device/wifi_util_pb2.py
spacex/api/device/wifi_util_pb2.pyi
spacex/api/device/wifi_util_pb2_grpc.py
spacex/api/device/__pycache__/command_pb2.cpython-313.pyc
spacex/api/device/__pycache__/common_pb2.cpython-313.pyc
spacex/api/device/__pycache__/device_pb2.cpython-313.pyc
spacex/api/device/__pycache__/dish_config_pb2.cpython-313.pyc
spacex/api/device/__pycache__/dish_pb2.cpython-313.pyc
spacex/api/device/__pycache__/rssi_scan_pb2.cpython-313.pyc
spacex/api/device/__pycache__/transceiver_pb2.cpython-313.pyc
spacex/api/device/__pycache__/wifi_config_pb2.cpython-313.pyc
spacex/api/device/__pycache__/wifi_pb2.cpython-313.pyc
spacex/api/device/__pycache__/wifi_util_pb2.cpython-313.pyc
spacex/api/device/services/unlock/service_pb2.py
spacex/api/device/services/unlock/service_pb2.pyi
starlink_client-0.1.13.dist-info/METADATA
starlink_client-0.1.13.dist-info/WHEEL
starlink_client-0.1.13.dist-info/top_level.txt
starlink_client-0.1.13.dist-info/RECORD
