Metadata-Version: 2.2
Name: starlink-client
Version: 0.1.13
Summary: A Python client for Starlink.
Home-page: https://github.com/Eitol/starlink-client
Author: Hector Oliveros
Author-email: hector.oliveros.leon@gmail.com
License: MIT
Keywords: starlink client grpc satellite internet antenna
Classifier: Programming Language :: Python :: 3
Classifier: License :: OSI Approved :: MIT License
Classifier: Operating System :: OS Independent
Classifier: Typing :: Typed
Requires-Python: >=3.9
Requires-Dist: grpcio
Requires-Dist: grpcio-status
Requires-Dist: proto-plus
Requires-Dist: protobuf
Requires-Dist: requests
Requires-Dist: httpx
Requires-Dist: pydantic
Requires-Dist: httpx[http2]
Dynamic: author
Dynamic: author-email
Dynamic: classifier
Dynamic: description
Dynamic: description-content-type
Dynamic: home-page
Dynamic: keywords
Dynamic: license
Dynamic: requires-dist
Dynamic: requires-python
Dynamic: summary
